rexpro/__init__.py
rexpro/VERSION
rexpro/messages.py
rexpro/_compat.py
rexpro/exceptions.py
rexpro/connection.py
rexpro/utils.py
rexpro/connectors/__init__.py
rexpro/connectors/base.py
rexpro/connectors/sync/__init__.py
rexpro/connectors/sync/connection.py
rexpro/connectors/rgevent/__init__.py
rexpro/connectors/rgevent/connection.py
rexpro/connectors/reventlet/__init__.py
rexpro/connectors/reventlet/connection.py
rexpro/tests/__init__.py
rexpro/tests/test_connection.py
rexpro/tests/base.py
rexpro/tests/test_utils.py
rexpro/tests/test_connection_pool.py
rexpro/tests/connectors/__init__.py
rexpro/tests/connectors/gevent_tests/__init__.py
rexpro/tests/connectors/gevent_tests/test_connection_drops.py
rexpro/tests/connectors/gevent_tests/test_concurrency.py
rexpro/tests/connectors/gevent_tests/test_connection_pool.py
rexpro/tests/connectors/sync_tests/__init__.py
rexpro/tests/connectors/sync_tests/test_connection_pool.py
rexpro/tests/connectors/eventlet_tests/__init__.py
rexpro/tests/connectors/eventlet_tests/test_connection_drops.py
rexpro/tests/connectors/eventlet_tests/test_concurrency.py
rexpro/tests/connectors/eventlet_tests/test_connection_pool.py
rexpro/tests/celerycheck/__init__.py
rexpro/tests/celerycheck/check_celery.py
rexpro/tests/celerycheck/tasks.py
rexpro/tests/celerycheck/celeryconfig.py
rexpro/tests/messages/__init__.py
rexpro/tests/messages/test_script_request.py
rexpro/tests/messages/test_session_request.py
rexpro-0.4.5.data/scripts/doc_builder.sh
rexpro-0.4.5.data/scripts/run_coverage.sh
rexpro-0.4.5.dist-info/METADATA
rexpro-0.4.5.dist-info/DESCRIPTION.rst
rexpro-0.4.5.dist-info/metadata.json
rexpro-0.4.5.dist-info/WHEEL
rexpro-0.4.5.dist-info/RECORD
rexpro-0.4.5.dist-info/dependency_links.txt
rexpro-0.4.5.dist-info/top_level.txt
