Metadata-Version: 2.0
Name: rexpro
Version: 0.4.5
Summary: Python RexPro interface
Home-page: https://github.com/platinummonkey/rexpro-python
Author: Cody Lee
Author-email: codylee@wellaware.us
License: BSD
Keywords: rexster,tinkerpop,rexpro,graphdb
Platform: UNKNOWN
Classifier: License :: OSI Approved :: BSD License
Classifier: Operating System :: OS Independent
Classifier: Programming Language :: Python :: 2.6
Classifier: Programming Language :: Python :: 2.7
Classifier: Topic :: Database
Classifier: Topic :: Database :: Front-Ends
Classifier: Topic :: Software Development :: Libraries :: Python Modules
Requires-Dist: msgpack-python (>=0.4.0)
Requires-Dist: six (>=1.6.1)
Provides-Extra: develop
Requires-Dist: nose (==1.3.0); extra == 'develop'
Requires-Dist: coverage (==3.7.1); extra == 'develop'
Requires-Dist: tox (==1.7.1); extra == 'develop'
Requires-Dist: celery (==3.1.11); extra == 'develop'
Requires-Dist: redis (==2.9.1); extra == 'develop'
Requires-Dist: tox (>=1.7.1); extra == 'develop'
Requires-Dist: detox (>=0.9.3); extra == 'develop'
Requires-Dist: gevent (>=1.0); extra == 'develop'
Requires-Dist: eventlet (>=0.14.0); extra == 'develop'
Requires-Dist: Sphinx (>=1.2.2); extra == 'develop'
Requires-Dist: watchdog (>=0.7.1); extra == 'develop'
Requires-Dist: sphinx-rtd-theme (>=0.1.6); extra == 'develop'
Provides-Extra: docs
Requires-Dist: Sphinx (>=1.2.2); extra == 'docs'
Requires-Dist: watchdog (>=0.7.1); extra == 'docs'
Requires-Dist: sphinx-rtd-theme (>=0.1.6); extra == 'docs'
Provides-Extra: eventlet
Requires-Dist: eventlet (>=0.14.0); extra == 'eventlet'
Provides-Extra: gevent
Requires-Dist: gevent (>=1.0); extra == 'gevent'
